cherryml/__init__.py
cherryml/__main__.py
cherryml/_cherryml_public_api.py
cherryml/_siterm_public_api.py
cherryml/config.py
cherryml/constants_neurips.py
cherryml/global_vars.py
cherryml/types.py
cherryml/utils.py
cherryml/_siterm/__init__.py
cherryml/_siterm/_cherryml_vectorized.py
cherryml/_siterm/_learn_site_rate_matrix.py
cherryml/_siterm/_site_specific_rate_matrix.py
cherryml/_siterm/_utils.py
cherryml/_siterm/fast_site_rates.cpp
cherryml/_siterm/fast_site_rates.cpython-310-darwin.so
cherryml/_siterm/fast_site_rates.pyx
cherryml/_siterm/_data/__init__.py
cherryml/_siterm/_maximum_parsimony/maximum_parsimony.cpp
cherryml/benchmarking/__init__.py
cherryml/benchmarking/globals.py
cherryml/benchmarking/lg_paper.py
cherryml/benchmarking/pfam_15k.py
cherryml/benchmarking/_contact_generation/ContactMatrix.py
cherryml/benchmarking/_contact_generation/__init__.py
cherryml/caching/__init__.py
cherryml/caching/_cached.py
cherryml/caching/_cached_computation.py
cherryml/caching/_cached_parallel_computation.py
cherryml/caching/_common.py
cherryml/counting/__init__.py
cherryml/counting/_count_co_transitions.cpp
cherryml/counting/_count_co_transitions.py
cherryml/counting/_count_transitions.cpp
cherryml/counting/_count_transitions.py
cherryml/estimation/__init__.py
cherryml/estimation/_em_lg.py
cherryml/estimation/_em_lg_xrate.py
cherryml/estimation/_jtt_ipw.py
cherryml/estimation/_quantized_transitions_mle.py
cherryml/estimation/_ratelearn/__init__.py
cherryml/estimation/_ratelearn/rate.py
cherryml/estimation/_ratelearn/ratelearner.py
cherryml/estimation/_ratelearn/simulate.py
cherryml/estimation/_ratelearn/trainer.py
cherryml/estimation_end_to_end/__init__.py
cherryml/estimation_end_to_end/_cherry.py
cherryml/estimation_end_to_end/_em.py
cherryml/evaluation/__init__.py
cherryml/evaluation/__main__.py
cherryml/evaluation/_evaluation_public_api.py
cherryml/evaluation/_likelihood.py
cherryml/evaluation/_maximal_matching.py
cherryml/evaluation/_metrics.py
cherryml-0.2.0.dist-info/LICENSE
cherryml-0.2.0.dist-info/METADATA
cherryml-0.2.0.dist-info/WHEEL
cherryml-0.2.0.dist-info/top_level.txt
cherryml-0.2.0.dist-info/RECORD
