Metadata-Version: 2.2
Name: cherryml
Version: 0.2.0
License-File: LICENSE
Requires-Dist: biotite
Requires-Dist: black
Requires-Dist: ete3
Requires-Dist: flake8
Requires-Dist: isort
Requires-Dist: matplotlib
Requires-Dist: networkx
Requires-Dist: numpy
Requires-Dist: pandas
Requires-Dist: parameterized
Requires-Dist: pytest
Requires-Dist: scipy
Requires-Dist: seaborn
Requires-Dist: threadpoolctl
Requires-Dist: torch
Requires-Dist: tqdm
Requires-Dist: wget
Dynamic: requires-dist
